{"id":"ac2c92f3-3c64-4751-8a9c-85c67400d27b","type":"flow","title":"富研社","message":"從夢想到財富。","labels":[],"labelsFrom":[],"whoOwnMe":[],"createdDate":"2018-10-31T16:56:48.017Z","editedDate":"2018-12-04T20:51:23.858Z","deletedDate":"","favorite":true,"clickRate":28,"itemContent":"","flowContent":[{"id":"-LA128F12BrrPhvB5r-v","type":"item","title":"財富自由、財務自由","message":"財富自由的定義和路徑。\n\n你是否做好了財富自由的準備?\n\n劳动不能创造财富，财富是通过交换来创造的。\n\n个人赚取收入的本质是：出售时间。\n\n个人收入 = 每天可售时间数量 * 单位时间价格 * 单位时间出售次数。\n\n在跳出來前腦袋裡只想著要『自由』，跳出來後你才發現你真正需要的是『自律』。"},{"id":"-L8U4PJIzlARoIlVobBJ","type":"flow","title":"重定義、概念重塑","message":"通过切换自己的思维来重新改造。\n\n\"当我们在谈论游戏的时候，我们在谈论什么？\""},{"id":"8b0298f8-bff8-4c78-b517-1229af940684","type":"flow","title":"腦力提升","message":""},{"id":"c32ddb39-4d62-4b12-8539-cc44ddf0b483","type":"flow","title":"效率升級","message":""},{"id":"a7089669-07a6-4a56-9e55-1cf6a3257380","type":"flow","title":"創造財富","message":""}]}